CirclesGenderDetectionPython/__init__.py
CirclesGenderDetectionPython/gender_detection
CirclesGenderDetectionPython/gender_detection.py
CirclesGenderDetectionPython/main.py
CirclesGenderDetectorPython-0.0.3.dist-info/METADATA
CirclesGenderDetectorPython-0.0.3.dist-info/WHEEL
CirclesGenderDetectorPython-0.0.3.dist-info/top_level.txt
CirclesGenderDetectorPython-0.0.3.dist-info/RECORD
