Metadata-Version: 2.1
Name: CirclesGenderDetectorPython
Version: 0.0.3
Summary: PyPI Package for gender detection
Home-page: https://github.com/circles-zone/gender-detection-local-python-package/tree/BU-1358-Convert-Python-Class-into-PyPi-Python-Module
Author: Circles
Author-email: info@circles.zone
Classifier: Programming Language :: Python :: 3
Classifier: License :: Other/Proprietary License
Classifier: Operating System :: OS Independent
